setup.py
siegfried/__init__.py
siegfried/main.py
siegfried/regex.py
siegfried.egg-info/PKG-INFO
siegfried.egg-info/SOURCES.txt
siegfried.egg-info/dependency_links.txt
siegfried.egg-info/namespace_packages.txt
siegfried.egg-info/not-zip-safe
siegfried.egg-info/requires.txt
siegfried.egg-info/top_level.txt