Metadata-Version: 1.1
Name: siegfried
Version: 0.2.0
Summary: Tools for taming lynx.
Home-page: http://github.com/newslynx/siegfried
Author: Brian Abelson
Author-email: brian@newslynx.org
License: MIT
Keywords: urls
Platform: UNKNOWN
Classifier: Development Status :: 3 - Alpha
Classifier: Intended Audience :: Developers
Classifier: License :: OSI Approved :: MIT License
Classifier: Operating System :: OS Independent
Classifier: Programming Language :: Python
